jenkinsnotify
