Metadata-Version: 1.1
Name: jenkins-notify
Version: 0.1.3
Summary: Jenkins build server desktop notification application
Home-page: http://github.com/samueljackson92/jenkins-notify
Author: Samuel Jackson
Author-email: samueljackson@outlook.com
License: UNKNOWN
Platform: UNKNOWN
Classifier: Development Status :: 3 - Alpha
Classifier: Environment :: Console
Classifier: Environment :: Web Environment
Classifier: Intended Audience :: Developers
Classifier: Natural Language :: English
Classifier: Operating System :: MacOS :: MacOS X
Classifier: Operating System :: POSIX :: Linux
Classifier: Programming Language :: Python
Classifier: Topic :: Software Development
